zljmail/__init__.py
zljmail/skeleton.py
zljmail-0.0.0.dist-info/AUTHORS.rst
zljmail-0.0.0.dist-info/LICENSE.txt
zljmail-0.0.0.dist-info/METADATA
zljmail-0.0.0.dist-info/WHEEL
zljmail-0.0.0.dist-info/top_level.txt
zljmail-0.0.0.dist-info/RECORD
